MANIFEST.in
backend_shim.py
setup.py
integrate_ai/__init__.py
integrate_ai/cli.py
integrate_ai/client.py
integrate_ai/main.py
integrate_ai/onprem_node.py
integrate_ai/sdk.py
integrate_ai/server.py
integrate_ai.egg-info/PKG-INFO
integrate_ai.egg-info/SOURCES.txt
integrate_ai.egg-info/dependency_links.txt
integrate_ai.egg-info/entry_points.txt
integrate_ai.egg-info/namespace_packages.txt
integrate_ai.egg-info/requires.txt
integrate_ai.egg-info/top_level.txt
integrate_ai/utils/__init__.py
integrate_ai/utils/docker_client.py
integrate_ai/utils/error_handling.py
integrate_ai/utils/logger.py
integrate_ai/utils/path_utils.py
integrate_ai/utils/rest_client.py
integrate_ai/utils/typer_utils.py