Metadata-Version: 2.1
Name: integrate_ai
Version: 9.22.3
Summary: integrate.ai
Author: integrate.ai
License: Copyright (C) 2022 integrate.ai, Inc. All rights reserved.
Classifier: Programming Language :: Python :: 3
Requires-Python: >=3.7.5
Requires-Dist: docker==7.1.0
Requires-Dist: pyjwt>=2.4.0
Requires-Dist: requests<3.0.0,>=2.32.2
Requires-Dist: rich<14.0.0,>=13.3.4
Requires-Dist: typer<0.8.0,>=0.7.0
